{"name": "dp83848", "namespace": "espressif", "created_at": "2025-09-24T13:45:31.068796+00:00", "featured": false, "versions": [{"id": "3b13f092-0fc2-4393-a958-7f2e69f83eb0", "version": "1.0.0", "created_at": "2025-09-24T13:45:33.590722+00:00", "description": "DP83848 Ethernet PHY Driver", "component_hash": "03cf03af6191c4789fca3eeef1a02aff78d896fecf138f45f9c2ec54863adc7e", "url": "components/espressif/dp83848/1.0.0/espressif__dp83848-v1.0.0.zip", "targets": ["esp32", "esp32p4"], "maintainers": [], "docs": {"readme": "components/espressif/dp83848/1.0.0/readme.md", "changelog": "components/espressif/dp83848/1.0.0/changelog.md"}, "dependencies": [{"spec": ">=6.0", "source": "idf", "registry_url": null, "is_public": false, "require": true, "name": null, "namespace": null, "rules": [], "matches": []}], "license": {"name": "Apache-2.0", "url": "components/espressif/dp83848/1.0.0/license.txt"}, "homepage": "https://github.com/espressif/esp-eth-drivers/tree/master/dp83848", "documentation": null, "repository": "git://github.com/espressif/esp-eth-drivers.git", "issues": null, "discussion": null, "examples": [], "tags": [], "downloads_total": 0, "checksums": "components/espressif/dp83848/1.0.0/CHECKSUMS.json", "yanked_at": null, "yanked_message": null, "build_metadata_keys": ["dependencies-*-type:string", "targets-type:array-type:string", "version-type:string"], "info_metadata_keys": ["description-type:string", "repository-type:string", "repository_info-commit_sha-type:string", "repository_info-path-type:string", "url-type:string"]}]}