{"name": "w5500", "namespace": "espressif", "created_at": "2025-09-24T11:51:23.545014+00:00", "featured": false, "versions": [{"id": "b75f3a8d-bf03-42c6-911d-d4e1b4cbfd24", "version": "1.0.1", "created_at": "2025-12-08T12:34:53.371561+00:00", "description": "W5500 Ethernet Driver", "component_hash": "e6e47022a1f509d1d1197652a554aea84a8cd4d99161061e187ecf4b78a7f6ca", "url": "components/espressif/w5500/1.0.1/espressif__w5500-v1.0.1.zip", "targets": [], "maintainers": [], "docs": {"readme": "components/espressif/w5500/1.0.1/readme.md", "changelog": "components/espressif/w5500/1.0.1/changelog.md"}, "dependencies": [{"spec": ">=6.0", "source": "idf", "registry_url": null, "is_public": false, "require": true, "name": null, "namespace": null, "rules": [], "matches": []}], "license": {"name": "Apache-2.0", "url": "components/espressif/w5500/1.0.1/license.txt"}, "homepage": "https://github.com/espressif/esp-eth-drivers/tree/master/w5500", "documentation": null, "repository": "git://github.com/espressif/esp-eth-drivers.git", "issues": null, "discussion": null, "examples": [{"id": "fd551711-f365-48f3-b898-bfc92eeb13ef", "name": "common_examples/iperf", "url": "8814152b-3df4-4f76-a14a-831da4d2ce97/examples/fd551711-f365-48f3-b898-bfc92eeb13ef.tgz", "docs": {"readme": "components/espressif/w5500/1.0.1/examples/common_examples/iperf/readme.md"}, "description": "This example provides a simple way to measure network performance using iperf, which includes command line interface functionality and DHCP server\u2026"}, {"id": "f16e0350-abd6-4e6e-a819-0d04b783fb37", "name": "common_examples/simple-ethernet", "url": "8814152b-3df4-4f76-a14a-831da4d2ce97/examples/f16e0350-abd6-4e6e-a819-0d04b783fb37.tgz", "docs": {}, "description": null}, {"id": "05208b3c-0bd4-4073-8f31-a356091aaf49", "name": "common_examples/tcp_client", "url": "8814152b-3df4-4f76-a14a-831da4d2ce97/examples/05208b3c-0bd4-4073-8f31-a356091aaf49.tgz", "docs": {"readme": "components/espressif/w5500/1.0.1/examples/common_examples/tcp_client/readme.md"}, "description": "This example provides a basic implementation of a TCP client for the ESP32 SoC family that periodically transmits a 'Hello message' to the server and\u2026"}, {"id": "0173bf39-2764-4867-a410-c75609928f12", "name": "common_examples/tcp_server", "url": "8814152b-3df4-4f76-a14a-831da4d2ce97/examples/0173bf39-2764-4867-a410-c75609928f12.tgz", "docs": {"readme": "components/espressif/w5500/1.0.1/examples/common_examples/tcp_server/readme.md"}, "description": "This example provides a basic implementation of a TCP server for the ESP32 SoC family with Ethernet drivers. It accepts transmissions from clients,\u2026"}], "tags": [], "downloads_total": 0, "checksums": "components/espressif/w5500/1.0.1/CHECKSUMS.json", "yanked_at": null, "yanked_message": null, "build_metadata_keys": ["dependencies-*-type:string", "version-type:string"], "info_metadata_keys": ["description-type:string", "repository-type:string", "repository_info-commit_sha-type:string", "repository_info-path-type:string", "url-type:string"]}]}